nutmegredundancysolver/__init__.py
nutmegredundancysolver/delete_script.py
nutmegredundancysolver/description_synthesis.py
nutmegredundancysolver/redundancy_solver.py
nutmegredundancysolver/test/test_description_synthesis.py
nutmegredundancysolver/test/test_redundancy_solver.py
nutmegredundancysolver-0.0.13.dist-info/METADATA
nutmegredundancysolver-0.0.13.dist-info/WHEEL
nutmegredundancysolver-0.0.13.dist-info/top_level.txt
nutmegredundancysolver-0.0.13.dist-info/RECORD
