Metadata-Version: 2.1
Name: nutmegredundancysolver
Version: 0.0.13
Author: James Baker
Author-email: james@talentium.io
License: MIT
Classifier: Programming Language :: Python :: 3
Classifier: License :: OSI Approved :: MIT License
Classifier: Operating System :: OS Independent
Requires-Dist: sumy ==0.11.0
Requires-Dist: strsimpy ==0.2.1
Requires-Dist: rouge-score ==0.1.2
Requires-Dist: scipy >=1.11.1
Requires-Dist: searchdatamodels >=0.0.59
Requires-Dist: evaluate >=0.4.0
Requires-Dist: mongomock >=4.1.2
Requires-Dist: pymongo >=4.5.0
